setup.cfg
setup.py
emrclient/__init__.py
emrclient/__main__.py
emrclient/cli.py
emrclient/config.py
emrclient/yarncli.py
emrclient.egg-info/PKG-INFO
emrclient.egg-info/SOURCES.txt
emrclient.egg-info/dependency_links.txt
emrclient.egg-info/entry_points.txt
emrclient.egg-info/requires.txt
emrclient.egg-info/top_level.txt