Metadata-Version: 1.1
Name: emrclient
Version: 0.3
Summary: This is created to view and kill applications/jobs running on yarn inside Amazon EMR or any other remote location. Currently the amazon api does not include stopping jobs. Also supports deploying steps
Home-page: https://github.com/zalando/emrclient
Author: Mark Kelly
Author-email: mkelly28@tcd.ie
License: Apache License 2.0
Download-URL: https://github.com/zalando/emrclient/tarball/0.0.3
Keywords: emr,aws,yarn,kill,view,client,spark,api
Platform: UNKNOWN
